{"human immunodeficiency virus": [["male", [NaN, -51.15625, -83.375, -96.0, -68.5625, -83.0625, -70.0, -84.8125, NaN, NaN, NaN, NaN, NaN, NaN, NaN, NaN, NaN, NaN, NaN, NaN]], ["female", [-53.71875, -52.875, -87.1875, -102.4375, -68.875, -84.125, -70.0, -85.8125, NaN, NaN, NaN, NaN, NaN, NaN, NaN, NaN, -138.0, -129.625, NaN, -146.625]], ["non-binary", [NaN, NaN, NaN, NaN, NaN, NaN, NaN, NaN, NaN, NaN, -187.875, NaN, NaN, NaN, NaN, NaN, NaN, NaN, NaN, NaN]]], "2019 novel coronavirus": [["male", [-48.875, -49.125, -76.25, -92.4375, -64.8125, -79.4375, -67.4375, -79.3125, NaN, -72.875, NaN, NaN, -115.5, -126.9375, -114.25, -103.0, -129.25, -119.625, NaN, -138.375]], ["female", [-51.46875, -48.5625, -80.3125, -96.6875, -66.875, -81.6875, -68.6875, -81.875, NaN, NaN, NaN, NaN, NaN, NaN, NaN, NaN, -131.625, -116.875, NaN, -142.75]], ["non-binary", [NaN, NaN, NaN, NaN, NaN, NaN, NaN, NaN, NaN, NaN, NaN, NaN, NaN, NaN, NaN, NaN, NaN, NaN, NaN, NaN]]], "takotsubo cardiomyopathy": [["male", [-76.125, -75.625, -99.75, -123.75, -91.375, -107.0, -92.6875, -106.375, NaN, -100.625, NaN, NaN, -132.875, -159.75, -145.5, -124.25, NaN, NaN, NaN, NaN]], ["female", [-75.6875, -72.4375, -100.75, -126.4375, -90.25, -111.375, -90.625, -106.25, NaN, NaN, NaN, NaN, NaN, NaN, NaN, NaN, NaN, NaN, NaN, NaN]], ["non-binary", [NaN, NaN, NaN, NaN, NaN, NaN, NaN, NaN, NaN, NaN, -211.625, NaN, NaN, NaN, NaN, NaN, NaN, NaN, NaN, NaN]]], "tuberculoses": [["male", [NaN, NaN, NaN, NaN, NaN, NaN, NaN, NaN, NaN, NaN, NaN, NaN, NaN, NaN, NaN, NaN, NaN, NaN, NaN, NaN]], ["female", [NaN, NaN, NaN, NaN, NaN, NaN, NaN, NaN, NaN, NaN, NaN, NaN, NaN, NaN, NaN, NaN, -148.25, -141.625, NaN, -157.625]], ["non-binary", [NaN, NaN, NaN, NaN, NaN, NaN, NaN, NaN, NaN, NaN, -201.25, NaN, NaN, NaN, NaN, NaN, NaN, NaN, NaN, NaN]]], "endocarditis": [["male", [-56.25, -53.0, -91.3125, -102.0, -72.125, -90.5, -71.5, -84.5, NaN, -79.0625, NaN, NaN, NaN, -137.875, -126.1875, -114.875, -142.25, -135.0, NaN, -154.0]], ["female", [-60.96875, -54.25, -93.3125, -103.875, -72.9375, -93.0625, -70.9375, -87.75, NaN, NaN, NaN, NaN, NaN, NaN, NaN, NaN, NaN, NaN, NaN, NaN]], ["non-binary", [-77.125, -73.4375, -116.0, -122.25, -90.875, -107.3125, -90.875, -108.9375, NaN, -102.25, NaN, NaN, -147.125, -158.375, -147.375, -134.625, -166.875, -157.375, NaN, -172.25]]], "syphilis": [["male", [-66.8125, -59.625, -97.125, -114.6875, -76.375, -97.5625, -76.75, -90.6875, NaN, NaN, NaN, NaN, NaN, NaN, NaN, NaN, -158.75, -147.0, NaN, -162.25]], ["female", [-68.4375, -61.34375, NaN, -122.0, -77.1875, -104.875, -75.9375, -90.3125, NaN, NaN, NaN, NaN, NaN, NaN, NaN, NaN, -158.25, -146.75, NaN, -163.0]], ["non-binary", [NaN, NaN, NaN, NaN, NaN, NaN, NaN, NaN, NaN, NaN, NaN, NaN, NaN, NaN, NaN, NaN, -181.875, -171.0, NaN, -189.375]]], "hypertension": [["male", [-40.125, -50.625, -70.1875, -82.625, -67.875, -71.0, -65.375, -81.25, NaN, NaN, NaN, NaN, NaN, NaN, NaN, NaN, -121.9375, -111.375, NaN, -130.75]], ["female", [-43.28125, -50.6875, -72.5625, -88.5625, -67.1875, -75.5625, -66.25, -79.6875, NaN, -71.625, NaN, NaN, -109.0625, -115.8125, -106.75, -95.875, -121.625, -115.5625, NaN, -137.25]], ["non-binary", [NaN, NaN, NaN, NaN, NaN, NaN, NaN, NaN, NaN, -93.0625, NaN, NaN, -132.875, -139.5, -124.875, NaN, -142.75, -138.5, NaN, -152.625]]], "sarcoid": [["male", [-47.5625, -53.46875, -79.125, -99.875, -69.4375, -82.125, -68.375, -83.375, NaN, NaN, NaN, NaN, NaN, NaN, NaN, NaN, -135.125, -132.5, NaN, -140.75]], ["female", [-48.9375, -53.1875, -88.8125, -97.125, -68.3125, -87.3125, -67.5, -84.4375, NaN, NaN, NaN, NaN, NaN, NaN, NaN, NaN, -137.125, -128.125, NaN, -147.75]], ["non-binary", [NaN, -79.6875, -97.625, -112.875, -84.3125, -90.375, -88.375, -103.0625, NaN, NaN, NaN, NaN, NaN, NaN, NaN, NaN, -157.625, -161.75, NaN, -162.875]]], "hepatitis b": [["male", [NaN, -60.4375, -75.8125, NaN, -75.75, -76.5, -73.0625, -93.25, NaN, NaN, NaN, NaN, NaN, NaN, NaN, NaN, -124.9375, -115.375, NaN, -136.25]], ["female", [-47.90625, -60.375, -74.6875, -93.4375, -78.0625, -82.875, -78.875, -95.25, NaN, NaN, NaN, NaN, NaN, NaN, NaN, NaN, NaN, NaN, NaN, NaN]], ["non-binary", [NaN, NaN, NaN, NaN, NaN, NaN, NaN, NaN, NaN, NaN, NaN, NaN, NaN, NaN, NaN, NaN, -147.375, -144.25, NaN, -155.375]]], "ulcerative colitis": [["male", [-58.6875, -69.9375, -95.5625, -108.5625, -87.1875, -99.6875, -86.5, -103.4375, NaN, NaN, NaN, NaN, NaN, NaN, NaN, NaN, -151.375, -142.5, NaN, -162.5]], ["female", [-62.3125, -68.875, -100.3125, -115.875, -87.875, -103.0, -86.75, -104.25, NaN, NaN, NaN, NaN, NaN, NaN, NaN, NaN, -152.625, -141.125, NaN, -164.0]], ["non-binary", [-80.5625, -94.4375, -119.5625, -124.9375, -113.6875, -111.875, -112.6875, -131.375, NaN, NaN, NaN, NaN, NaN, NaN, NaN, NaN, -173.625, -166.5, NaN, -177.25]]], "crohn disease": [["male", [-61.21875, -51.46875, -96.3125, -107.125, -69.5625, -96.8125, -69.1875, -84.9375, NaN, NaN, NaN, NaN, NaN, NaN, NaN, NaN, -148.0, -142.0, NaN, -157.5]], ["female", [-63.03125, -53.40625, -99.125, -113.0625, -69.125, -95.5, -69.75, -84.8125, NaN, NaN, NaN, NaN, NaN, NaN, NaN, NaN, -148.375, -143.375, NaN, -156.625]], ["non-binary", [NaN, -79.125, -122.5625, -132.375, -93.625, -111.8125, -96.375, -114.0, NaN, NaN, -194.75, NaN, NaN, NaN, NaN, NaN, -168.75, -167.125, NaN, -178.25]]], "chagas disease": [["male", [NaN, NaN, NaN, NaN, NaN, NaN, NaN, NaN, NaN, NaN, NaN, NaN, NaN, NaN, NaN, NaN, NaN, NaN, NaN, NaN]], ["female", [-62.6875, -51.78125, -87.1875, -114.125, -69.25, -97.5, -71.6875, -84.8125, NaN, NaN, NaN, NaN, NaN, NaN, NaN, NaN, NaN, NaN, NaN, NaN]], ["non-binary", [NaN, NaN, -113.5625, NaN, NaN, NaN, NaN, NaN, NaN, NaN, NaN, NaN, NaN, NaN, NaN, NaN, NaN, NaN, NaN, NaN]]], "diastolic dysfunction": [["male", [-45.59375, -61.34375, -76.4375, -86.875, -80.0, -78.625, -78.6875, -93.8125, NaN, NaN, NaN, NaN, NaN, NaN, NaN, NaN, -132.0, -119.75, NaN, -136.125]], ["female", [-47.5625, -63.21875, -77.6875, -93.5, -80.6875, -79.8125, -80.0, -94.4375, NaN, -87.25, NaN, NaN, -114.1875, -123.0, -117.125, -100.25, -131.125, -120.6875, NaN, -136.125]], ["non-binary", [NaN, NaN, NaN, NaN, NaN, NaN, NaN, NaN, NaN, -112.5, -177.0, NaN, -135.125, -139.875, -132.75, -121.0, -153.0, -141.375, NaN, -159.0]]], "goiter": [["male", [-47.625, -47.59375, -82.75, -93.5625, -63.53125, -83.125, -64.375, -79.4375, NaN, NaN, NaN, NaN, NaN, NaN, NaN, NaN, -131.75, -124.625, NaN, -139.875]], ["female", [-53.34375, -49.25, -81.5, -97.5, -66.125, -85.5, -65.5625, -81.8125, NaN, NaN, NaN, NaN, NaN, NaN, NaN, NaN, -132.125, -125.375, NaN, -141.625]], ["non-binary", [-67.125, -73.4375, -97.5, -114.8125, -85.6875, -99.9375, -85.875, -99.5, NaN, NaN, NaN, NaN, NaN, NaN, NaN, NaN, -152.25, -150.25, NaN, NaN]]], "arthritis": [["male", [-38.5625, -55.0, -67.375, -84.75, -74.1875, -69.0625, -72.5, -86.4375, NaN, NaN, NaN, NaN, NaN, NaN, NaN, NaN, -119.625, -108.4375, NaN, -130.75]], ["female", [-43.96875, -55.6875, -69.125, -85.9375, -73.75, -72.5, -73.5625, -87.75, NaN, NaN, NaN, NaN, NaN, NaN, NaN, NaN, -119.75, -111.875, NaN, -134.0]], ["non-binary", [NaN, NaN, NaN, NaN, NaN, NaN, NaN, NaN, NaN, NaN, -170.0, NaN, NaN, NaN, NaN, NaN, -140.625, -135.75, NaN, -146.875]]], "repetitive stress syndrome": [["male", [-45.0625, -66.5, -69.1875, -89.625, -82.0625, -75.0, -80.5, -94.1875, NaN, NaN, NaN, NaN, NaN, NaN, NaN, NaN, -127.25, -122.0625, NaN, -135.875]], ["female", [-47.3125, -67.8125, -73.625, -94.375, -82.4375, -80.0, -83.1875, -97.0625, NaN, NaN, NaN, NaN, NaN, NaN, NaN, NaN, NaN, NaN, NaN, NaN]], ["non-binary", [NaN, NaN, NaN, NaN, NaN, NaN, NaN, NaN, NaN, NaN, NaN, NaN, NaN, NaN, NaN, NaN, -152.25, -152.125, NaN, -158.5]]], "flu": [["male", [NaN, NaN, NaN, NaN, NaN, NaN, NaN, NaN, NaN, NaN, NaN, NaN, NaN, NaN, NaN, NaN, -116.3125, -105.8125, NaN, -128.25]], ["female", [NaN, NaN, NaN, NaN, NaN, NaN, NaN, NaN, NaN, NaN, NaN, NaN, NaN, NaN, NaN, NaN, -115.3125, -111.625, NaN, -129.625]], ["non-binary", [NaN, NaN, NaN, NaN, NaN, NaN, NaN, NaN, NaN, NaN, NaN, NaN, NaN, NaN, NaN, NaN, -138.0, -137.25, NaN, -149.5]]], "suicide": [["male", [-37.875, -43.15625, -67.625, -82.0, -60.65625, -67.125, -59.125, -73.9375, NaN, NaN, NaN, NaN, NaN, NaN, NaN, NaN, NaN, NaN, NaN, NaN]], ["female", [-39.15625, -43.90625, -68.9375, -84.8125, -61.21875, -70.25, -59.5, -76.25, NaN, NaN, NaN, NaN, NaN, NaN, NaN, NaN, -115.375, -114.625, NaN, -130.625]], ["non-binary", [-55.09375, -70.4375, -88.9375, -98.625, -82.75, -84.375, -83.0, -96.9375, NaN, NaN, NaN, NaN, NaN, NaN, NaN, NaN, -137.875, -130.875, NaN, -147.75]]], "visual anomalies": [["male", [-43.25, -48.1875, -76.0625, -88.8125, -60.96875, -73.8125, -62.65625, -76.125, NaN, NaN, NaN, NaN, NaN, NaN, NaN, NaN, -123.75, -121.3125, NaN, -136.75]], ["female", [-46.875, -48.0625, -75.625, -88.5, -62.75, -76.6875, -65.1875, -79.0, NaN, NaN, NaN, NaN, NaN, NaN, NaN, NaN, -124.875, -121.75, NaN, -139.375]], ["non-binary", [NaN, NaN, NaN, NaN, NaN, NaN, NaN, NaN, NaN, NaN, NaN, NaN, NaN, NaN, NaN, NaN, -145.5, -139.25, NaN, -157.875]]], "loss of sex drive": [["male", [NaN, -56.8125, -90.6875, -107.4375, -77.0625, -98.875, -75.75, -95.125, NaN, NaN, NaN, NaN, NaN, NaN, NaN, NaN, -144.5, -138.375, NaN, -156.75]], ["female", [-67.75, -64.4375, -93.5625, -111.4375, -80.5625, -100.0, -77.4375, -98.375, NaN, NaN, NaN, NaN, NaN, NaN, NaN, NaN, -147.125, -137.875, NaN, -153.875]], ["non-binary", [NaN, -82.6875, -114.875, -128.25, -94.125, -114.625, -92.8125, -116.125, NaN, -106.9375, NaN, NaN, -148.125, -161.0, -150.5, -140.0, -165.125, -165.625, NaN, -170.625]]], "spotting problems": [["male", [-55.78125, -58.15625, -82.75, -99.5, -75.0625, -85.0, -74.625, -92.1875, NaN, NaN, NaN, NaN, NaN, NaN, NaN, NaN, -136.25, -131.125, NaN, -149.25]], ["female", [-58.375, -60.1875, -86.1875, -102.625, -77.6875, -88.75, -77.0625, -92.75, NaN, NaN, NaN, NaN, NaN, NaN, NaN, NaN, -135.5, -127.0, NaN, -150.625]], ["non-binary", [-69.0, -84.9375, -109.375, -113.4375, -98.1875, -102.375, -99.8125, -115.5, NaN, -108.5, -191.125, NaN, -143.25, -155.25, -143.375, -135.625, -158.125, -156.75, NaN, -165.625]]], "perforated ulcer": [["male", [NaN, NaN, NaN, NaN, NaN, NaN, NaN, NaN, NaN, NaN, NaN, NaN, NaN, NaN, NaN, NaN, NaN, NaN, NaN, NaN]], ["female", [-60.1875, -63.0625, NaN, -107.25, -79.375, -95.9375, -80.125, -96.125, NaN, NaN, NaN, NaN, NaN, NaN, NaN, NaN, NaN, NaN, NaN, NaN]], ["non-binary", [NaN, NaN, NaN, NaN, NaN, NaN, NaN, NaN, NaN, NaN, NaN, NaN, NaN, NaN, NaN, NaN, NaN, NaN, NaN, NaN]]], "ibs": [["male", [-54.65625, -47.40625, -81.1875, -96.875, -60.75, -78.625, -62.46875, -77.25, NaN, -70.6875, NaN, NaN, -116.75, -123.3125, -116.625, -105.875, -130.375, -124.75, NaN, -140.625]], ["female", [-54.625, -48.6875, -81.375, -101.4375, -61.9375, -82.875, -63.9375, -78.625, NaN, -69.6875, NaN, NaN, -116.75, -125.0, -119.25, -108.0625, -132.125, -126.0625, NaN, -142.875]], ["non-binary", [NaN, -71.375, -95.375, -112.5, -83.5625, -95.125, -85.0, -102.3125, NaN, -92.25, -178.75, NaN, -136.375, -148.25, -137.5, -131.75, -150.25, -153.875, NaN, -158.125]]], "acne": [["male", [-38.5625, -45.25, -66.6875, -82.5625, -62.3125, -67.0625, -60.28125, -75.9375, NaN, NaN, NaN, NaN, NaN, NaN, NaN, NaN, -119.625, -110.9375, NaN, -130.125]], ["female", [-40.59375, -48.25, -64.0, -84.0, -61.4375, -70.6875, -61.71875, -76.0, NaN, -69.375, NaN, NaN, -108.875, -112.9375, -102.75, -95.6875, -121.0625, -110.4375, NaN, -133.25]], ["non-binary", [-56.03125, -70.0, -90.8125, -100.875, -80.1875, -82.3125, -82.5, -96.25, NaN, NaN, NaN, NaN, NaN, NaN, NaN, NaN, -140.875, -132.875, NaN, -152.125]]], "achilles tendinitis": [["male", [-85.25, -69.875, -119.5, -133.25, -89.125, -120.1875, -87.125, -105.5, NaN, NaN, NaN, NaN, NaN, NaN, NaN, NaN, -166.5, -158.875, NaN, -177.5]], ["female", [-88.9375, -69.25, -122.4375, -137.5, -88.8125, -125.0, -87.5, -106.1875, NaN, -96.75, NaN, NaN, -152.375, -157.75, -149.0, -143.625, -164.75, -161.125, NaN, -175.625]], ["non-binary", [-104.5625, -95.625, -144.625, -154.0, -118.0625, -135.0, -114.75, -130.375, NaN, -121.9375, NaN, NaN, -180.25, -183.375, NaN, -168.375, -188.875, -183.625, NaN, -197.5]]], "bipolar disorder": [["male", [-39.15625, -48.9375, -72.8125, -82.75, -65.375, -71.9375, -62.46875, -81.875, NaN, NaN, NaN, NaN, NaN, NaN, NaN, NaN, NaN, NaN, NaN, NaN]], ["female", [-41.59375, -51.03125, -71.25, -88.6875, -67.75, -75.625, -66.75, -81.0, NaN, NaN, NaN, NaN, NaN, NaN, NaN, NaN, -124.9375, -118.875, NaN, -136.25]], ["non-binary", [NaN, NaN, NaN, NaN, NaN, NaN, NaN, -106.1875, NaN, NaN, NaN, NaN, NaN, NaN, NaN, NaN, NaN, NaN, NaN, NaN]]], "hyperthyroid": [["male", [-48.6875, -45.78125, -76.4375, -97.8125, -60.5, -85.3125, -60.15625, -75.1875, NaN, NaN, NaN, NaN, NaN, NaN, NaN, NaN, -138.5, -126.0, NaN, -142.125]], ["female", [NaN, NaN, NaN, NaN, NaN, NaN, NaN, NaN, NaN, NaN, NaN, NaN, NaN, NaN, NaN, NaN, -137.125, -130.5, NaN, -145.5]], ["non-binary", [NaN, NaN, NaN, NaN, NaN, NaN, NaN, NaN, NaN, NaN, NaN, NaN, NaN, NaN, NaN, NaN, -158.0, -153.125, NaN, -167.25]]], "hypothyroid": [["male", [NaN, NaN, NaN, NaN, NaN, NaN, NaN, NaN, NaN, NaN, NaN, NaN, NaN, NaN, NaN, NaN, NaN, NaN, NaN, NaN]], ["female", [NaN, NaN, NaN, NaN, NaN, NaN, NaN, NaN, NaN, NaN, NaN, NaN, NaN, NaN, NaN, NaN, NaN, NaN, NaN, NaN]], ["non-binary", [NaN, NaN, NaN, NaN, NaN, NaN, NaN, NaN, NaN, NaN, NaN, NaN, NaN, NaN, NaN, NaN, NaN, NaN, NaN, NaN]]], "acute kidney failure": [["male", [-52.09375, -51.53125, -90.8125, -98.0, -69.8125, -82.4375, -70.25, -82.375, NaN, NaN, NaN, NaN, NaN, NaN, NaN, NaN, NaN, NaN, NaN, NaN]], ["female", [-55.25, -53.4375, -89.25, -100.1875, -70.625, -87.0625, -70.9375, -89.0625, NaN, NaN, NaN, NaN, NaN, NaN, NaN, NaN, -136.5, -130.625, NaN, -148.625]], ["non-binary", [NaN, NaN, NaN, NaN, NaN, NaN, NaN, NaN, NaN, NaN, NaN, NaN, NaN, NaN, NaN, NaN, NaN, NaN, NaN, NaN]]], "deafness": [["male", [NaN, -52.5, -73.1875, -94.125, -68.75, -78.3125, -66.1875, -83.0625, NaN, NaN, NaN, NaN, NaN, NaN, NaN, NaN, -130.0, -121.1875, NaN, -146.5]], ["female", [NaN, -57.28125, -77.5, -94.875, -71.875, -82.375, -70.75, -86.875, NaN, NaN, NaN, NaN, NaN, NaN, NaN, NaN, -129.625, -123.0, NaN, -141.5]], ["non-binary", [NaN, -77.0625, -100.125, -108.8125, -89.0, -93.375, -88.75, -106.0625, NaN, NaN, NaN, NaN, NaN, NaN, NaN, NaN, -151.25, -150.5, NaN, -157.125]]], "hypochondria": [["male", [-61.84375, -52.125, -94.375, -110.125, -70.75, -98.5625, -71.4375, -85.5625, NaN, -79.25, NaN, NaN, -142.0, -141.75, -130.625, -117.625, NaN, NaN, NaN, NaN]], ["female", [NaN, -49.40625, -95.5625, -117.125, -67.9375, -96.125, -70.8125, -82.5, NaN, NaN, NaN, NaN, NaN, NaN, NaN, NaN, -153.625, -144.625, NaN, -163.875]], ["non-binary", [NaN, NaN, NaN, NaN, NaN, NaN, NaN, NaN, NaN, NaN, -198.125, NaN, NaN, NaN, NaN, NaN, -175.5, -173.875, NaN, -177.125]]], "gingival disease": [["male", [-58.28125, -59.15625, -96.875, -109.375, -76.6875, -94.625, -75.5625, -88.5625, NaN, NaN, NaN, NaN, NaN, NaN, NaN, NaN, -146.875, -140.625, NaN, -154.125]], ["female", [-58.84375, -58.75, -97.0, -107.875, -75.6875, -96.375, -77.125, -92.5, NaN, NaN, NaN, NaN, NaN, NaN, NaN, NaN, -147.375, -137.75, NaN, -155.5]], ["non-binary", [NaN, NaN, NaN, NaN, NaN, NaN, NaN, NaN, NaN, NaN, NaN, NaN, NaN, NaN, NaN, NaN, -167.125, -162.125, NaN, -174.25]]], "disability": [["male", [-38.15625, -47.625, -64.9375, -78.3125, -64.125, -68.875, -63.34375, -81.75, NaN, NaN, NaN, NaN, NaN, NaN, NaN, NaN, -116.1875, -107.375, NaN, -130.25]], ["female", [-40.75, -47.625, -66.5, -82.8125, -64.5625, -72.5, -63.8125, -80.3125, NaN, NaN, NaN, NaN, NaN, NaN, NaN, NaN, -114.6875, -113.875, NaN, -129.625]], ["non-binary", [NaN, NaN, NaN, NaN, NaN, NaN, NaN, NaN, NaN, NaN, NaN, NaN, NaN, NaN, NaN, NaN, -136.625, -134.0, NaN, -146.25]]], "osteoarthritis": [["male", [NaN, NaN, NaN, NaN, NaN, NaN, NaN, NaN, NaN, NaN, NaN, NaN, NaN, NaN, NaN, NaN, -132.625, -128.125, NaN, -145.75]], ["female", [NaN, NaN, NaN, NaN, NaN, NaN, NaN, NaN, NaN, NaN, NaN, NaN, NaN, NaN, NaN, NaN, -130.125, -125.1875, NaN, -146.0]], ["non-binary", [NaN, NaN, NaN, NaN, NaN, NaN, NaN, NaN, NaN, NaN, -180.5, NaN, NaN, NaN, NaN, NaN, -154.75, -148.375, NaN, -162.625]]], "mi": [["male", [NaN, NaN, -68.6875, -85.625, NaN, NaN, NaN, NaN, NaN, NaN, -148.5, NaN, NaN, NaN, NaN, NaN, -122.0, -113.625, NaN, -131.75]], ["female", [-42.75, -41.21875, -63.9375, -87.25, -55.15625, -74.0, -55.65625, -71.4375, NaN, NaN, NaN, NaN, NaN, NaN, NaN, NaN, -123.5, -112.6875, NaN, -125.0625]], ["non-binary", [NaN, NaN, NaN, -104.3125, NaN, NaN, NaN, NaN, NaN, NaN, -176.875, NaN, NaN, NaN, NaN, NaN, -141.375, -132.25, NaN, -148.25]]], "lyme disease": [["male", [-64.25, -55.125, -93.4375, -112.625, -73.3125, -96.6875, -73.6875, -87.5, NaN, NaN, NaN, NaN, NaN, NaN, NaN, NaN, -143.125, -139.75, NaN, -156.375]], ["female", [-66.0, -56.28125, -96.75, -110.6875, -74.375, -100.5625, -73.25, -89.8125, NaN, -81.375, NaN, NaN, -128.625, -139.25, -129.625, -122.125, -147.5, -137.375, NaN, -159.125]], ["non-binary", [-78.125, -82.375, -120.4375, -129.875, -97.9375, -112.4375, -98.3125, -111.5, NaN, NaN, NaN, NaN, NaN, NaN, NaN, NaN, -166.875, -165.125, NaN, -176.375]]], "labyrinthitis": [["male", [-52.21875, -57.5625, -81.6875, -101.1875, -71.875, -85.9375, -70.1875, -86.5625, NaN, NaN, NaN, NaN, NaN, NaN, NaN, NaN, -137.125, -131.625, NaN, -150.25]], ["female", [-56.0, -58.875, -90.25, -105.75, -72.0, -88.25, -73.6875, -87.3125, NaN, NaN, NaN, NaN, NaN, NaN, NaN, NaN, -138.0, -129.0, NaN, -150.125]], ["non-binary", [NaN, -81.9375, -111.625, -119.0, -96.5625, -101.5, -96.6875, -113.625, NaN, -104.875, -192.5, NaN, -146.5, -159.875, -150.375, -139.625, -159.0, -150.125, NaN, -171.625]]], "fibromyalgia": [["male", [-57.375, -57.875, -96.5, -103.75, -73.375, -94.25, -75.8125, -87.125, NaN, NaN, NaN, NaN, NaN, NaN, NaN, NaN, -149.5, -136.0, NaN, -160.25]], ["female", [-61.875, -53.5, -91.4375, -109.6875, -69.4375, -92.1875, -71.5, -83.5625, NaN, NaN, NaN, NaN, NaN, NaN, NaN, NaN, -153.75, -135.375, NaN, -158.375]], ["non-binary", [NaN, NaN, NaN, NaN, NaN, NaN, NaN, NaN, NaN, NaN, NaN, NaN, NaN, NaN, NaN, NaN, -173.25, -157.125, NaN, -173.5]]], "multiple sclerosis": [["male", [-48.46875, -50.46875, -82.0, -95.4375, -65.625, NaN, -65.75, -83.9375, NaN, NaN, NaN, NaN, NaN, NaN, NaN, NaN, -130.5, -126.75, NaN, -140.125]], ["female", [-51.46875, -50.03125, -82.8125, -98.8125, -66.0625, -84.125, -69.375, -85.9375, NaN, NaN, NaN, NaN, NaN, NaN, NaN, NaN, -133.125, -123.625, NaN, -143.25]], ["non-binary", [NaN, NaN, NaN, NaN, NaN, NaN, NaN, NaN, NaN, -100.5625, -184.875, NaN, -139.375, -144.75, -137.0, -130.5, -155.625, -143.5, NaN, -160.625]]], "acute gastritis": [["male", [-63.875, -59.6875, -96.75, -104.0, -77.625, -92.3125, -77.25, -89.5, NaN, NaN, NaN, NaN, NaN, NaN, NaN, NaN, -150.125, -142.375, NaN, -152.625]], ["female", [-68.25, -62.1875, -99.375, -107.625, -77.3125, -100.3125, -78.1875, -90.5, NaN, NaN, NaN, NaN, NaN, NaN, NaN, NaN, -152.25, -134.25, NaN, -159.875]], ["non-binary", [NaN, NaN, NaN, NaN, NaN, NaN, NaN, NaN, NaN, NaN, NaN, NaN, NaN, NaN, NaN, NaN, -169.75, -167.25, NaN, -182.25]]], "muscle inflammation": [["male", [-45.78125, -52.65625, -74.75, -91.125, -68.8125, -78.0625, -69.0625, -85.25, NaN, -77.8125, NaN, NaN, -111.75, -120.4375, -110.5625, -97.5, -127.8125, -117.1875, NaN, -140.875]], ["female", [-47.5625, -53.78125, -78.875, -93.5, -73.5, -78.8125, -70.25, -86.9375, NaN, -78.1875, NaN, NaN, -117.5625, -118.125, -114.25, -104.5, -128.375, -125.3125, NaN, -138.5]], ["non-binary", [NaN, -77.875, -98.1875, -108.0, -95.1875, -94.625, -96.875, -113.25, NaN, -104.375, NaN, NaN, -135.375, -147.5, -137.0, -125.75, -150.125, -144.625, NaN, -158.25]]], "alzheimer's": [["male", [-64.6875, -55.78125, -92.0, -108.5625, -69.125, -98.5, -68.0, -86.375, NaN, NaN, NaN, NaN, NaN, NaN, NaN, NaN, NaN, NaN, NaN, NaN]], ["female", [-66.6875, -56.96875, -97.375, -111.6875, -72.125, -95.5, -71.375, -85.1875, NaN, NaN, NaN, NaN, NaN, NaN, NaN, NaN, NaN, NaN, NaN, NaN]], ["non-binary", [NaN, NaN, NaN, -132.875, NaN, NaN, NaN, NaN, NaN, NaN, -192.125, NaN, NaN, NaN, NaN, NaN, -164.125, -166.125, NaN, -171.375]]], "gastric problems": [["male", [-46.1875, -57.0, -71.25, -87.75, -76.3125, -76.75, -76.25, -87.9375, NaN, NaN, NaN, NaN, NaN, NaN, NaN, NaN, -130.25, -120.9375, NaN, -137.125]], ["female", [-48.46875, -60.15625, -75.625, -93.0625, -75.3125, -80.3125, -76.9375, -92.0, NaN, NaN, NaN, NaN, NaN, NaN, NaN, NaN, -130.5, -121.875, NaN, -137.625]], ["non-binary", [NaN, NaN, NaN, NaN, NaN, NaN, NaN, -112.125, NaN, NaN, NaN, NaN, NaN, NaN, NaN, NaN, -149.625, -149.125, NaN, -162.0]]], "oesophageal ulcer": [["male", [-62.21875, -55.375, -96.3125, -117.3125, -73.375, -100.625, -72.625, -89.8125, NaN, NaN, NaN, NaN, NaN, NaN, NaN, NaN, -159.375, -146.625, NaN, -165.625]], ["female", [-67.375, -56.875, -101.4375, -119.5625, -75.1875, -105.5625, -75.125, -88.1875, NaN, NaN, NaN, NaN, NaN, NaN, NaN, NaN, NaN, NaN, NaN, NaN]], ["non-binary", [NaN, -78.0, -121.5, -131.125, -103.3125, -115.0, -97.3125, -113.5, NaN, NaN, NaN, NaN, NaN, NaN, NaN, NaN, -177.875, -166.0, NaN, -185.5]]], "polymyositis": [["male", [-65.8125, -65.0625, -100.375, -109.6875, -82.6875, -103.25, -80.875, -97.1875, NaN, NaN, NaN, NaN, NaN, NaN, NaN, NaN, -160.875, -147.25, NaN, -155.375]], ["female", [-67.125, -64.5625, -99.3125, -118.625, -82.625, -109.3125, -84.3125, -101.1875, NaN, NaN, NaN, NaN, NaN, NaN, NaN, NaN, -156.0, -144.25, NaN, -158.375]], ["non-binary", [-77.1875, -86.8125, -119.5625, -128.25, -106.625, -114.375, -103.25, -123.625, NaN, -113.6875, NaN, NaN, -161.25, -171.25, -154.375, -150.75, -174.125, -180.5, NaN, -181.375]]], "bronchitis": [["male", [-52.1875, -51.59375, -79.625, -96.875, -67.375, -82.875, -67.9375, -84.5625, NaN, NaN, NaN, NaN, NaN, NaN, NaN, NaN, -134.625, -124.625, NaN, -144.5]], ["female", [-51.96875, -53.4375, -78.3125, -96.6875, -71.375, -84.625, -69.1875, -85.75, NaN, NaN, NaN, NaN, NaN, NaN, NaN, NaN, -133.0, -122.375, NaN, -146.125]], ["non-binary", [NaN, NaN, NaN, NaN, NaN, NaN, NaN, NaN, NaN, NaN, NaN, NaN, NaN, NaN, NaN, NaN, -156.375, -153.375, NaN, -164.625]]], "parkinson's disease": [["male", [-55.375, -61.28125, -91.375, -110.0625, -77.0, -88.3125, -76.8125, -94.875, NaN, NaN, NaN, NaN, NaN, NaN, NaN, NaN, -136.625, -136.75, NaN, -152.5]], ["female", [-59.46875, -62.75, -86.875, -107.75, -78.25, -89.9375, -78.5625, -94.8125, NaN, NaN, NaN, NaN, NaN, NaN, NaN, NaN, -140.25, -133.375, NaN, -148.25]], ["non-binary", [NaN, NaN, NaN, NaN, NaN, NaN, NaN, NaN, NaN, NaN, NaN, NaN, NaN, NaN, NaN, NaN, -160.125, -151.5, NaN, -172.75]]], "restless legs syndrome": [["male", [-52.0625, -64.6875, -85.4375, -96.9375, -83.1875, -88.25, -81.875, -93.8125, NaN, NaN, NaN, NaN, NaN, NaN, NaN, NaN, -135.875, -125.625, NaN, -148.375]], ["female", [-54.46875, -67.375, -85.1875, -103.875, -83.1875, -87.75, -83.6875, -99.3125, NaN, NaN, NaN, NaN, NaN, NaN, NaN, NaN, -137.375, -131.375, NaN, -151.375]], ["non-binary", [NaN, NaN, NaN, NaN, NaN, NaN, NaN, NaN, NaN, NaN, NaN, NaN, NaN, NaN, NaN, NaN, -157.625, -156.125, NaN, -171.0]]], "inflammatory disorder of tendon": [["male", [NaN, -63.71875, -89.5625, NaN, -79.75, NaN, -81.4375, -97.125, NaN, -85.3125, NaN, NaN, -127.1875, -129.875, -127.625, -108.8125, -140.625, -136.5, NaN, -151.75]], ["female", [NaN, -64.875, -85.0625, NaN, -80.5625, NaN, -80.9375, -93.1875, NaN, -88.0, NaN, NaN, -131.375, -134.125, -125.625, -114.125, -137.25, -134.25, NaN, -152.0]], ["non-binary", [NaN, NaN, NaN, NaN, NaN, NaN, NaN, NaN, NaN, NaN, NaN, NaN, NaN, NaN, NaN, NaN, -159.5, -161.125, NaN, -175.75]]], "mood disorder of depressed type": [["male", [-64.375, -69.625, -90.9375, -111.4375, -86.125, -97.3125, -85.0625, -101.625, NaN, -94.875, NaN, NaN, -133.5, -136.5, -127.9375, -119.0625, -150.0, -141.125, NaN, -158.125]], ["female", [-68.8125, -68.625, -93.25, -116.625, -85.1875, -102.4375, -85.625, -103.0, NaN, -92.5, NaN, NaN, -131.875, -142.875, -130.875, -120.6875, -147.0, -137.25, NaN, -160.625]], ["non-binary", [-79.875, -97.1875, -112.4375, -128.75, -109.5625, -114.0, -110.625, -125.875, NaN, -117.8125, -200.625, NaN, -154.25, -164.875, -151.0, -145.5, -166.875, -163.5, NaN, -179.125]]], "sinus infection": [["male", [-43.59375, -52.125, -70.0, -86.8125, -69.375, -74.5625, -72.0625, -86.8125, NaN, NaN, NaN, NaN, NaN, NaN, NaN, NaN, -126.6875, -114.375, NaN, -135.0]], ["female", [-45.9375, -53.25, -70.5, -91.0, -70.375, -78.8125, -71.5625, -87.6875, NaN, NaN, NaN, NaN, NaN, NaN, NaN, NaN, -124.6875, -119.1875, NaN, -138.5]], ["non-binary", [NaN, NaN, NaN, NaN, NaN, NaN, NaN, NaN, NaN, -103.3125, NaN, NaN, -134.375, -145.25, -134.5, -126.125, -144.5, -143.875, NaN, -160.875]]], "mnd": [["male", [-53.90625, -46.0625, -81.375, -93.875, -58.5625, -81.5625, -61.375, -73.75, NaN, -67.4375, -158.75, NaN, -113.75, -124.5, -117.25, -104.75, -129.5, -117.5, NaN, -136.875]], ["female", [-57.09375, -43.625, -78.375, -96.875, -59.28125, -84.0, -60.375, -72.625, NaN, NaN, NaN, NaN, NaN, NaN, NaN, NaN, -128.75, -121.875, NaN, -142.375]], ["non-binary", [-65.6875, -67.4375, -94.875, -109.75, -74.875, -93.3125, -79.0625, -93.5625, NaN, -82.0, NaN, NaN, -136.0, -144.25, -135.5, -127.6875, -149.75, -147.5, NaN, -162.875]]], "permanent nerve damage": [["male", [-47.0, -66.25, -78.75, -95.375, -80.625, -82.25, -81.875, -98.125, NaN, NaN, NaN, NaN, NaN, NaN, NaN, NaN, NaN, NaN, NaN, NaN]], ["female", [-51.4375, -64.875, -82.375, -96.1875, -80.5, -83.625, -81.125, -96.625, NaN, NaN, NaN, NaN, NaN, NaN, NaN, NaN, NaN, NaN, NaN, NaN]], ["non-binary", [-68.75, -93.3125, -105.3125, -111.25, -106.4375, -95.3125, -106.0, -123.8125, NaN, NaN, NaN, NaN, NaN, NaN, NaN, NaN, -153.75, -147.375, NaN, -163.125]]], "gall bladder disease": [["male", [-50.1875, -54.5625, -79.1875, -95.4375, -73.5, -83.0, -71.3125, -87.5, NaN, NaN, NaN, NaN, NaN, NaN, NaN, NaN, -134.5, -128.5, NaN, -146.0]], ["female", [-55.4375, -54.84375, -81.75, -101.4375, -75.1875, -85.1875, -72.5, -90.0625, NaN, NaN, NaN, NaN, NaN, NaN, NaN, NaN, NaN, NaN, NaN, NaN]], ["non-binary", [NaN, NaN, NaN, NaN, NaN, NaN, NaN, NaN, NaN, NaN, -186.875, NaN, NaN, NaN, NaN, NaN, NaN, NaN, NaN, NaN]]], "infection": [["male", [-38.625, -41.4375, -65.75, -80.0625, -59.53125, -66.8125, -57.9375, -69.9375, NaN, NaN, NaN, NaN, NaN, NaN, NaN, NaN, -118.125, -108.5625, NaN, -132.0]], ["female", [-41.875, -43.03125, -71.375, -84.5625, -59.90625, -70.625, -60.9375, -75.0625, NaN, NaN, NaN, NaN, NaN, NaN, NaN, NaN, NaN, NaN, NaN, NaN]], ["non-binary", [NaN, NaN, NaN, NaN, NaN, NaN, NaN, NaN, NaN, -91.25, NaN, NaN, -127.6875, -134.0, -121.375, -117.5, -136.0, -135.375, NaN, -148.5]]], "sepsis": [["male", [-39.59375, -48.28125, -67.5, -82.3125, -65.0, -68.1875, -64.375, -79.9375, NaN, -71.5625, NaN, NaN, -104.625, -112.125, -103.1875, -93.0625, -121.0, -108.4375, NaN, -131.75]], ["female", [-41.46875, -49.46875, -69.375, -87.5625, -66.0, -71.4375, -64.1875, -81.3125, NaN, NaN, NaN, NaN, NaN, NaN, NaN, NaN, -121.375, -113.6875, NaN, -132.5]], ["non-binary", [NaN, NaN, NaN, NaN, NaN, NaN, NaN, NaN, NaN, -93.3125, NaN, NaN, -121.8125, -136.375, -125.8125, -121.25, -140.0, -136.125, NaN, -148.5]]], "menopause": [["male", [-48.90625, -49.28125, -81.125, -90.9375, -67.1875, -81.0, -67.3125, -80.0625, NaN, NaN, NaN, NaN, NaN, NaN, NaN, NaN, -128.75, -119.1875, NaN, -141.625]], ["female", [-51.21875, -50.03125, -83.125, -96.625, -69.1875, -84.9375, -68.0625, -81.9375, NaN, NaN, NaN, NaN, NaN, NaN, NaN, NaN, -131.125, -125.0, NaN, -138.5]], ["non-binary", [-63.3125, -73.5, -103.5, -109.1875, -92.125, -95.9375, -90.875, -104.1875, NaN, NaN, NaN, NaN, NaN, NaN, NaN, NaN, -151.375, -147.5, NaN, -159.0]]], "eczema": [["male", [-64.8125, -54.53125, -102.0, -112.625, -67.9375, -98.25, -70.8125, -82.4375, NaN, NaN, NaN, NaN, NaN, NaN, NaN, NaN, -154.875, -138.375, NaN, -160.875]], ["female", [-70.375, -56.21875, NaN, -116.125, -71.6875, -101.125, -70.625, -84.125, NaN, NaN, NaN, NaN, NaN, NaN, NaN, NaN, -150.125, -144.875, NaN, -165.375]], ["non-binary", [NaN, NaN, NaN, NaN, NaN, NaN, NaN, NaN, NaN, NaN, NaN, NaN, NaN, NaN, NaN, NaN, -170.25, -169.5, NaN, -178.75]]], "type two diabetic": [["male", [NaN, NaN, NaN, NaN, NaN, NaN, NaN, NaN, NaN, NaN, NaN, NaN, NaN, NaN, NaN, NaN, -139.0, -122.6875, NaN, -148.75]], ["female", [-54.40625, -54.65625, -83.5625, -102.625, -68.125, -90.5, -68.75, -82.1875, NaN, NaN, -168.875, NaN, NaN, NaN, NaN, NaN, -140.75, -129.625, NaN, -147.0]], ["non-binary", [NaN, NaN, NaN, -120.875, NaN, NaN, NaN, NaN, NaN, NaN, -188.75, NaN, NaN, NaN, NaN, NaN, -160.875, -155.125, NaN, -165.75]]], "type one diabetic": [["male", [-50.59375, -52.78125, -82.9375, -97.25, -69.25, -83.9375, -68.9375, -80.3125, NaN, -74.0625, -166.375, NaN, -124.625, -130.0, -117.25, NaN, -139.125, -131.375, NaN, -144.625]], ["female", [-53.25, -52.71875, -86.875, -103.625, -67.8125, -88.9375, -67.6875, -80.5625, NaN, NaN, NaN, NaN, NaN, NaN, NaN, NaN, -139.0, -129.625, NaN, -145.75]], ["non-binary", [NaN, NaN, NaN, NaN, NaN, NaN, NaN, NaN, NaN, NaN, -182.375, NaN, NaN, NaN, NaN, NaN, -158.75, -152.75, NaN, -163.125]]], "parkinson": [["male", [NaN, -47.3125, -72.4375, -90.75, -62.8125, -74.4375, -63.875, -79.125, NaN, NaN, NaN, NaN, NaN, NaN, NaN, NaN, -122.5, -117.75, NaN, -135.0]], ["female", [NaN, -47.8125, -75.9375, -91.4375, -64.5625, -78.4375, -65.25, -82.6875, NaN, NaN, NaN, NaN, NaN, NaN, NaN, NaN, -123.0625, -120.8125, NaN, -138.75]], ["non-binary", [NaN, NaN, NaN, NaN, NaN, NaN, NaN, NaN, NaN, NaN, -176.25, NaN, NaN, NaN, NaN, NaN, -142.25, -138.125, NaN, -159.125]]], "cardiovascular disease": [["male", [-41.78125, -43.6875, -74.9375, -86.1875, -63.09375, -72.875, -61.53125, -76.0625, NaN, NaN, NaN, NaN, NaN, NaN, NaN, NaN, -126.5625, -114.25, NaN, -136.125]], ["female", [-44.875, -44.6875, -75.375, -89.625, -63.46875, -76.1875, -63.15625, -76.8125, NaN, NaN, NaN, NaN, NaN, NaN, NaN, NaN, -125.1875, -115.3125, NaN, -135.75]], ["non-binary", [NaN, NaN, NaN, NaN, NaN, NaN, NaN, NaN, NaN, NaN, NaN, NaN, NaN, NaN, NaN, NaN, NaN, NaN, NaN, NaN]]], "learning problems": [["male", [-45.5, -54.0625, -75.3125, -88.375, -67.6875, -77.375, -67.3125, -83.875, NaN, -74.75, NaN, NaN, -119.625, -118.8125, -112.8125, -97.75, -129.5, -117.25, NaN, -137.625]], ["female", [-48.75, -54.59375, -76.9375, -91.5625, -69.25, -80.0, -67.9375, -83.1875, NaN, -73.0, NaN, NaN, -116.0625, -123.5625, -112.8125, -100.0, -128.75, -115.0, NaN, -142.25]], ["non-binary", [-60.5, -79.0, -97.875, -108.0625, -90.8125, -84.875, -87.1875, -109.375, NaN, -96.625, NaN, NaN, -129.875, -145.125, -135.375, -122.75, -149.875, -139.625, NaN, -159.125]]], "dementia": [["male", [-36.9375, -51.6875, -67.5, -79.625, -65.75, -67.0625, -63.625, -78.1875, NaN, NaN, NaN, NaN, NaN, NaN, NaN, NaN, -118.625, -106.625, NaN, -132.0]], ["female", [-39.375, -49.28125, -66.75, -81.1875, -64.9375, -68.875, -65.0625, -80.6875, NaN, NaN, NaN, NaN, NaN, NaN, NaN, NaN, -114.3125, -109.25, NaN, -128.875]], ["non-binary", [NaN, NaN, NaN, NaN, NaN, NaN, NaN, NaN, NaN, -92.9375, NaN, NaN, -121.4375, -132.0, -123.4375, -112.75, -134.0, -130.75, NaN, -149.375]]], "chronic fatigue syndrome": [["male", [-44.90625, -51.78125, -77.625, -91.25, -68.75, -78.125, -68.75, -83.125, NaN, NaN, NaN, NaN, NaN, NaN, NaN, NaN, -129.625, -122.5, NaN, -140.25]], ["female", [-47.1875, -53.8125, -77.5625, -96.0, -70.3125, -80.8125, -70.25, -86.625, NaN, NaN, NaN, NaN, NaN, NaN, NaN, NaN, -130.75, -122.625, NaN, -140.875]], ["non-binary", [NaN, NaN, NaN, NaN, NaN, NaN, NaN, -111.3125, NaN, NaN, NaN, NaN, NaN, NaN, NaN, NaN, -151.0, -150.0, NaN, -161.375]]], "coronary artery disease": [["male", [-48.0625, -64.0, -82.8125, -98.0, -79.9375, -85.25, -79.5625, -94.625, NaN, NaN, NaN, NaN, NaN, NaN, NaN, NaN, NaN, NaN, NaN, NaN]], ["female", [-52.40625, -67.5625, -83.6875, -102.0625, -80.4375, -85.0, -82.5625, -94.75, NaN, NaN, NaN, NaN, NaN, NaN, NaN, NaN, -135.25, -131.25, NaN, -145.75]], ["non-binary", [NaN, NaN, NaN, NaN, NaN, NaN, NaN, NaN, NaN, NaN, NaN, NaN, NaN, NaN, NaN, NaN, NaN, NaN, NaN, NaN]]], "upper respiratory infection": [["male", [-45.15625, -49.3125, -81.5625, -94.125, -69.375, -81.625, -67.3125, -83.9375, NaN, -75.375, NaN, NaN, -122.3125, -126.625, -115.3125, -106.4375, -134.125, -119.875, NaN, -141.75]], ["female", [-48.5625, -48.8125, -82.3125, -96.625, -68.375, -84.5625, -69.0, -84.625, NaN, NaN, NaN, NaN, NaN, NaN, NaN, NaN, -131.875, -125.5, NaN, -143.5]], ["non-binary", [NaN, NaN, NaN, NaN, NaN, NaN, NaN, NaN, NaN, -103.875, NaN, NaN, -141.375, -149.25, -136.75, -129.875, NaN, NaN, NaN, NaN]]], "alopecia": [["male", [-69.375, -54.4375, -110.8125, NaN, -71.375, -106.3125, -71.3125, -86.1875, NaN, -79.4375, NaN, NaN, -134.75, -139.375, -135.125, -128.125, -158.75, -149.625, NaN, -165.25]], ["female", [-71.0, -56.3125, -107.8125, -130.25, -71.125, -108.0625, -69.75, -87.875, NaN, NaN, NaN, NaN, NaN, NaN, NaN, NaN, -157.875, -147.625, NaN, -166.25]], ["non-binary", [-84.0, -82.6875, -127.6875, NaN, -94.75, -121.75, -93.125, -112.1875, NaN, NaN, NaN, NaN, NaN, NaN, NaN, NaN, -173.75, -174.875, NaN, -182.125]]], "sexual dysfunction": [["male", [-43.6875, -48.4375, -76.3125, -90.5625, -64.875, -77.1875, -66.875, -84.3125, NaN, NaN, NaN, NaN, NaN, NaN, NaN, NaN, -130.25, -120.1875, NaN, -136.875]], ["female", [-48.625, -50.96875, -79.6875, -94.3125, -68.875, -79.75, -68.6875, -84.125, NaN, NaN, NaN, NaN, NaN, NaN, NaN, NaN, -128.25, -118.5625, NaN, -139.375]], ["non-binary", [NaN, -73.875, -95.75, -110.75, -91.8125, -92.125, -90.1875, -106.75, NaN, -97.75, NaN, NaN, -135.75, -143.75, -134.5, -128.25, -151.875, -146.75, NaN, -162.625]]], "nerve damage": [["male", [-44.0, -54.1875, -76.1875, -87.4375, -66.0, -73.0625, -67.5, -86.5, NaN, NaN, NaN, NaN, NaN, NaN, NaN, NaN, NaN, NaN, NaN, NaN]], ["female", [-45.84375, -55.8125, -72.5, -94.25, -68.6875, -79.3125, -69.75, -86.5625, NaN, NaN, NaN, NaN, NaN, NaN, NaN, NaN, -126.0, -120.25, NaN, -140.125]], ["non-binary", [NaN, NaN, NaN, NaN, NaN, NaN, NaN, NaN, NaN, NaN, NaN, NaN, NaN, NaN, NaN, NaN, NaN, NaN, NaN, NaN]]], "carpal tunnel syndrome": [["male", [-50.4375, -53.625, -89.375, -106.6875, -72.125, -89.375, -73.0, -89.875, NaN, NaN, NaN, NaN, NaN, NaN, NaN, NaN, -143.75, -134.625, NaN, -152.375]], ["female", [-57.71875, -56.0, -86.6875, -109.3125, -74.6875, -91.0625, -74.875, -92.0, NaN, NaN, NaN, NaN, NaN, NaN, NaN, NaN, -143.875, -138.125, NaN, -155.625]], ["non-binary", [NaN, -79.0, -107.3125, -123.5625, -100.875, -100.875, -99.25, -114.3125, NaN, NaN, NaN, NaN, NaN, NaN, NaN, NaN, -165.0, -159.75, NaN, -182.5]]], "liver failure": [["male", [-44.96875, -50.5, -78.8125, -89.6875, -64.6875, -76.25, -64.6875, -81.75, NaN, NaN, NaN, NaN, NaN, NaN, NaN, NaN, -128.375, -120.3125, NaN, -136.125]], ["female", [-47.25, -51.53125, -80.25, -92.25, -64.6875, -79.5, -67.4375, -84.6875, NaN, NaN, NaN, NaN, NaN, NaN, NaN, NaN, -127.625, -121.5625, NaN, -141.875]], ["non-binary", [NaN, NaN, NaN, NaN, NaN, NaN, NaN, NaN, NaN, NaN, NaN, NaN, NaN, NaN, NaN, NaN, -146.375, -141.375, NaN, -160.5]]], "tinnitus": [["male", [-61.875, -57.0, -91.0, -114.125, -70.1875, -96.5625, -70.3125, -85.0, NaN, NaN, NaN, NaN, NaN, NaN, NaN, NaN, -151.875, -131.375, NaN, -161.625]], ["female", [-60.40625, -55.125, -94.8125, -114.6875, -73.1875, -95.75, -73.125, -88.25, NaN, NaN, NaN, NaN, NaN, NaN, NaN, NaN, -151.75, -136.125, NaN, -162.0]], ["non-binary", [-75.5, -80.0, -112.3125, -128.625, -94.3125, -113.125, -94.25, -111.4375, NaN, NaN, -194.25, NaN, NaN, NaN, NaN, NaN, -173.75, -159.25, NaN, -179.25]]], "malaria": [["male", [-37.65625, -51.0625, -71.125, -81.375, -68.375, -67.25, -66.5625, -82.0, NaN, NaN, NaN, NaN, NaN, NaN, NaN, NaN, -119.4375, -107.5625, NaN, -128.75]], ["female", [-38.71875, -51.03125, -65.625, -83.0, -68.5, -70.0, -66.5625, -84.25, NaN, NaN, NaN, NaN, NaN, NaN, NaN, NaN, -118.4375, -111.375, NaN, -132.0]], ["non-binary", [NaN, NaN, NaN, NaN, NaN, NaN, NaN, NaN, NaN, NaN, NaN, NaN, NaN, NaN, NaN, NaN, -138.75, -133.25, NaN, -151.375]]], "phlebitis": [["male", [-64.6875, -58.625, -93.4375, -117.5, -72.8125, -100.375, -75.0625, -87.9375, NaN, -78.0, NaN, NaN, -138.0, -144.5, -141.0, -120.1875, -157.125, -143.75, NaN, -160.375]], ["female", [-71.25, -57.40625, -94.1875, -122.5625, -70.0, -102.6875, -73.0, -85.6875, NaN, NaN, NaN, NaN, NaN, NaN, NaN, NaN, -159.0, -147.25, NaN, -164.75]], ["non-binary", [NaN, NaN, NaN, NaN, NaN, NaN, NaN, NaN, NaN, NaN, NaN, NaN, NaN, NaN, NaN, NaN, -176.5, -172.875, NaN, -179.875]]], "diarrhoea": [["male", [-76.4375, -67.25, -110.3125, -123.0625, -83.625, -114.6875, -83.0, -97.875, NaN, NaN, NaN, NaN, NaN, NaN, NaN, NaN, -170.0, NaN, NaN, -168.125]], ["female", [-79.625, -65.125, -109.6875, -123.875, -81.1875, -115.5625, -82.125, -99.625, NaN, NaN, NaN, NaN, NaN, NaN, NaN, NaN, -168.75, -168.0, NaN, -171.125]], ["non-binary", [-84.75, -90.5, NaN, -134.125, -107.0, -114.625, -104.75, -122.25, NaN, NaN, NaN, NaN, NaN, NaN, NaN, NaN, -191.125, NaN, NaN, -195.5]]], "vision problems": [["male", [-46.75, -48.21875, -70.375, -88.6875, -66.0, -74.1875, -64.1875, -80.25, NaN, -69.4375, NaN, NaN, -113.6875, -122.375, -111.5, -94.4375, -127.1875, -119.25, NaN, -140.0]], ["female", [-49.8125, -47.8125, -76.9375, -93.3125, -65.375, -80.75, -65.4375, -79.6875, NaN, -71.375, NaN, NaN, -113.8125, -122.25, -109.375, -99.8125, -129.875, -119.25, NaN, -139.5]], ["non-binary", [-63.34375, -71.0, -92.0625, -111.0, -86.1875, -93.75, -86.75, -104.0, NaN, NaN, -176.75, NaN, NaN, NaN, NaN, NaN, -149.25, -144.375, NaN, -160.625]]], "aortic aneurysem": [["male", [NaN, NaN, NaN, -125.0, NaN, NaN, NaN, NaN, NaN, NaN, NaN, NaN, NaN, NaN, NaN, NaN, NaN, NaN, NaN, NaN]], ["female", [NaN, NaN, NaN, -133.25, NaN, NaN, NaN, NaN, NaN, NaN, NaN, NaN, NaN, NaN, NaN, NaN, -163.25, -156.0, NaN, -166.5]], ["non-binary", [NaN, NaN, NaN, NaN, NaN, NaN, NaN, NaN, NaN, NaN, NaN, NaN, NaN, NaN, NaN, NaN, NaN, NaN, NaN, NaN]]], "urinary tract infection": [["male", [NaN, NaN, NaN, NaN, NaN, NaN, NaN, NaN, NaN, NaN, NaN, NaN, NaN, NaN, NaN, NaN, NaN, NaN, NaN, NaN]], ["female", [NaN, NaN, NaN, NaN, NaN, NaN, NaN, -87.625, NaN, NaN, NaN, NaN, NaN, NaN, NaN, NaN, NaN, NaN, NaN, NaN]], ["non-binary", [NaN, NaN, NaN, NaN, NaN, NaN, NaN, NaN, NaN, NaN, NaN, NaN, NaN, NaN, NaN, NaN, NaN, NaN, NaN, NaN]]], "psychosis": [["male", [-38.34375, -42.5625, -68.3125, -78.3125, -59.5, -69.875, -60.1875, -73.125, NaN, -66.3125, NaN, NaN, -102.25, -110.875, -101.5, -90.0625, -120.0, -108.75, NaN, -128.375]], ["female", [-40.78125, -45.90625, -66.9375, -85.375, -59.28125, -70.875, -59.21875, -73.5, NaN, -66.5625, NaN, NaN, -106.5625, -111.1875, -102.75, -96.875, -120.4375, -110.0, NaN, -133.25]], ["non-binary", [NaN, NaN, NaN, NaN, NaN, NaN, NaN, NaN, NaN, -87.5625, NaN, NaN, -126.875, -138.25, -125.25, -117.5, -139.125, -134.625, NaN, -148.0]]], "rheumatoid arthritis": [["male", [-44.25, -70.8125, -75.25, -88.5, -89.3125, -74.75, -86.5, -102.9375, NaN, NaN, NaN, NaN, NaN, NaN, NaN, NaN, NaN, NaN, NaN, NaN]], ["female", [-48.15625, -71.625, -78.3125, -93.8125, -85.75, -78.8125, -86.25, -104.625, NaN, NaN, NaN, NaN, NaN, NaN, NaN, NaN, NaN, NaN, NaN, NaN]], ["non-binary", [NaN, NaN, NaN, NaN, NaN, NaN, NaN, NaN, NaN, NaN, -176.375, NaN, NaN, NaN, NaN, NaN, NaN, NaN, NaN, NaN]]], "diabetes": [["male", [-38.0, -46.3125, -64.375, -83.5, -65.4375, -68.0625, -65.8125, -78.0, NaN, -70.0625, NaN, NaN, -104.375, -109.875, -100.625, -88.625, -116.3125, -105.8125, NaN, -130.0]], ["female", [-40.5625, -46.78125, -69.0, -87.375, -65.3125, -73.5, -63.1875, -78.1875, NaN, -70.0625, NaN, NaN, -104.625, -113.125, -104.75, -92.8125, -117.875, -115.125, NaN, -129.75]], ["non-binary", [NaN, NaN, NaN, NaN, NaN, NaN, NaN, NaN, NaN, NaN, NaN, NaN, NaN, NaN, NaN, NaN, -137.75, -131.875, NaN, -149.0]]], "stevens johnson syndrome": [["male", [-87.125, -76.5625, -117.8125, -143.625, -95.375, -128.625, -92.9375, -107.375, NaN, -102.875, NaN, NaN, -163.5, -176.625, -162.375, -152.0, -184.625, -167.25, NaN, -188.5]], ["female", [-93.625, -75.875, -124.125, -149.625, -89.875, -134.25, -90.75, -106.75, NaN, NaN, NaN, NaN, NaN, NaN, NaN, NaN, -182.375, -167.5, NaN, -189.875]], ["non-binary", [-101.625, -100.4375, -139.625, -158.875, -120.375, -144.375, -112.8125, -130.125, NaN, NaN, NaN, NaN, NaN, NaN, NaN, NaN, -209.25, -194.25, NaN, -209.125]]], "mental illness": [["male", [-42.59375, -47.125, -75.625, -90.375, -65.4375, -78.375, -65.6875, -81.9375, NaN, NaN, NaN, NaN, NaN, NaN, NaN, NaN, NaN, NaN, NaN, NaN]], ["female", [-44.9375, -48.5, -81.0625, -94.1875, -68.125, -80.625, -66.1875, -81.0625, NaN, NaN, NaN, NaN, NaN, NaN, NaN, NaN, NaN, NaN, NaN, NaN]], ["non-binary", [NaN, NaN, NaN, NaN, NaN, NaN, NaN, NaN, NaN, NaN, NaN, NaN, NaN, NaN, NaN, NaN, NaN, NaN, NaN, NaN]]], "pancreatitis": [["male", [NaN, NaN, NaN, NaN, NaN, NaN, NaN, NaN, NaN, NaN, NaN, NaN, NaN, NaN, NaN, NaN, NaN, NaN, NaN, NaN]], ["female", [-53.59375, -51.9375, -78.875, -96.5, -67.1875, -84.25, -72.0625, -83.625, NaN, NaN, NaN, NaN, NaN, NaN, NaN, NaN, -134.625, -123.375, NaN, -143.625]], ["non-binary", [NaN, NaN, NaN, NaN, NaN, NaN, NaN, NaN, NaN, NaN, NaN, NaN, NaN, NaN, NaN, NaN, NaN, NaN, NaN, NaN]]], "adenomyosis": [["male", [-51.90625, -61.46875, -79.75, -96.375, -79.5, -83.875, -80.75, -94.0625, NaN, NaN, NaN, NaN, NaN, NaN, NaN, NaN, NaN, NaN, NaN, NaN]], ["female", [-56.15625, -62.9375, -81.6875, -97.5625, -81.4375, -87.75, -78.1875, -94.75, NaN, NaN, NaN, NaN, NaN, NaN, NaN, NaN, NaN, NaN, NaN, NaN]], ["non-binary", [NaN, NaN, NaN, NaN, NaN, NaN, NaN, NaN, NaN, NaN, NaN, NaN, NaN, NaN, NaN, NaN, NaN, NaN, NaN, NaN]]], "als": [["male", [NaN, NaN, -67.3125, -86.125, NaN, NaN, NaN, NaN, NaN, -61.21875, NaN, NaN, -110.5625, -116.0625, -105.0625, -92.0, -122.375, -116.75, NaN, -132.125]], ["female", [-43.96875, -41.375, -63.21875, -88.5625, -53.40625, -76.6875, -53.46875, -67.8125, NaN, -62.46875, NaN, NaN, -112.75, -115.75, -106.0, -96.1875, -124.5, -119.25, NaN, -134.625]], ["non-binary", [NaN, NaN, NaN, -102.75, NaN, NaN, NaN, NaN, NaN, NaN, -175.125, NaN, NaN, NaN, NaN, NaN, -144.25, -145.375, NaN, -152.25]]], "chronic kidney disease": [["male", [-53.1875, -60.25, -85.375, -99.5, -74.375, -82.375, -73.1875, -84.5625, NaN, NaN, NaN, NaN, NaN, NaN, NaN, NaN, -133.25, -132.25, NaN, -145.5]], ["female", [-53.375, -58.8125, -86.875, -101.4375, -75.4375, -83.5625, -75.0, -89.5625, NaN, NaN, NaN, NaN, NaN, NaN, NaN, NaN, -134.25, -128.125, NaN, -145.25]], ["non-binary", [NaN, NaN, NaN, NaN, NaN, NaN, NaN, NaN, NaN, NaN, -181.75, NaN, NaN, NaN, NaN, NaN, -158.0, -154.625, NaN, -165.75]]], "endometriosis": [["male", [-48.21875, -65.25, -79.5, -94.0625, -77.3125, -80.875, -79.4375, -93.1875, NaN, NaN, NaN, NaN, NaN, NaN, NaN, NaN, -135.5, -126.4375, NaN, -144.5]], ["female", [-51.09375, -66.0625, -79.375, -98.5, -78.3125, -86.5, -78.0625, -92.3125, NaN, NaN, NaN, NaN, NaN, NaN, NaN, NaN, -136.25, -122.875, NaN, -147.5]], ["non-binary", [NaN, NaN, NaN, NaN, NaN, NaN, NaN, NaN, NaN, NaN, NaN, NaN, NaN, NaN, NaN, NaN, -152.625, -152.875, NaN, -166.25]]], "asthma": [["male", [-37.25, -55.5, -65.875, -82.5, -70.1875, -67.125, -72.5, -82.9375, NaN, NaN, NaN, NaN, NaN, NaN, NaN, NaN, -117.875, -108.3125, NaN, -126.9375]], ["female", [-41.75, -54.65625, -68.1875, -86.5, -69.875, -71.9375, -68.75, -82.6875, NaN, NaN, NaN, NaN, NaN, NaN, NaN, NaN, -120.25, -114.1875, NaN, -133.0]], ["non-binary", [NaN, NaN, NaN, NaN, NaN, NaN, NaN, NaN, NaN, NaN, NaN, NaN, NaN, NaN, NaN, NaN, -140.375, -134.5, NaN, -152.375]]], "lupus": [["male", [-38.59375, -51.8125, -70.25, -79.625, -66.4375, -67.875, -66.25, -82.6875, NaN, NaN, NaN, NaN, NaN, NaN, NaN, NaN, -119.6875, -108.5625, NaN, -127.4375]], ["female", [-39.3125, -53.34375, -69.0, -83.8125, -65.1875, -69.0625, -65.625, -80.8125, NaN, NaN, NaN, NaN, NaN, NaN, NaN, NaN, -119.125, -112.3125, NaN, -128.625]], ["non-binary", [-54.59375, -76.75, -88.125, -99.25, -85.5625, -83.3125, -86.1875, -106.375, NaN, -98.0, NaN, NaN, -125.9375, -136.125, -127.9375, -115.1875, -138.0, -136.75, NaN, -147.125]]], "pneumonia": [["male", [-38.53125, -57.40625, -67.25, -81.5, -72.0625, -71.0, -71.875, -85.875, NaN, -80.125, NaN, NaN, -101.75, -107.8125, -99.4375, -87.6875, -115.0, -106.75, NaN, -129.375]], ["female", [-40.4375, -56.53125, -68.25, -85.125, -72.875, -71.0625, -75.625, -89.0625, NaN, NaN, NaN, NaN, NaN, NaN, NaN, NaN, -118.125, -114.125, NaN, -131.25]], ["non-binary", [NaN, NaN, NaN, NaN, NaN, NaN, NaN, NaN, NaN, -108.625, -165.0, NaN, -121.25, -135.625, -126.875, -116.6875, -135.125, -134.625, NaN, -147.875]]], "arrhythmia": [["male", [NaN, NaN, NaN, NaN, NaN, NaN, NaN, NaN, NaN, -76.1875, NaN, NaN, NaN, NaN, NaN, -113.0, NaN, NaN, NaN, -152.375]], ["female", [-61.625, -51.3125, -90.875, -106.1875, -68.625, NaN, -70.5625, -86.0, NaN, NaN, NaN, NaN, NaN, NaN, NaN, NaN, NaN, NaN, NaN, -148.875]], ["non-binary", [NaN, NaN, NaN, NaN, NaN, NaN, NaN, NaN, NaN, NaN, NaN, NaN, NaN, NaN, NaN, NaN, NaN, NaN, NaN, NaN]]]}